RBHTTPAuthBackend
