Metadata-Version: 1.0
Name: RBHTTPAuthBackend
Version: 0.2
Summary: reviewboard http auth module
Home-page: UNKNOWN
Author: Ali-Akber Saifee
Author-email: ali@indydevs.org
License: UNKNOWN
Platform: UNKNOWN
